{
  "comments": [
    {
      "id": "4",
      "name": "MANASA",
      "email": "my@gmail.com",
      "body": "hello this is manasa how are you doing today"
    },
    {
      "id": "1",
      "name": "Namah",
      "email": "nama@gmail.com",
      "body": "Hi this is namah"
    },
    {
      "id": "5",
      "name": "KLM",
      "email": "klm@gmail.com",
      "body": "Hi this is KLM"
    },
    {
      "id": "2",
      "name": "Ramya",
      "email": "ram@gmail.com",
      "body": "Hi this is Ramya"
    },
    {
      "id": "3",
      "name": "Madhu",
      "email": "Madhu@gmail.com",
      "body": "Hi This is Madhu"
    }
  ]
}